[
    {
        "_id": "5465338bf06f7a651feab3e5",
        "index": 0,
        "guid": "2867a192-94de-4465-ba50-b27879c3fd9f",
        "isActive": true,
        "picture": "http://placehold.it/32x32",
        "age": 39,
        "name": "Bobbi Holman",
        "gender": "female",
        "email": "bobbiholman@telequiet.com",
        "about": "Officia magna consectetur culpa culpa eu tempor irure eiusmod ad cillum. Eiusmod mollit magna duis amet. Laboris commodo nulla aliquip eu exercitation magna pariatur elit exercitation in. Aliquip anim consequat in deserunt ut tempor nisi consectetur adipisicing voluptate in. Proident commodo in minim ullamco et mollit fugiat consequat. Non est cillum consectetur tempor sunt eiusmod labore do pariatur reprehenderit ipsum eu. Cillum et veniam dolore occaecat nostrud proident ea velit incididunt.\r\n",
        "registered": "2014-11-12T11:16:34 -01:00",
        "friends": [
            {
                "id": 0,
                "name": "Holder Battle"
            },
            {
                "id": 1,
                "name": "Lucia Wells"
            },
            {
                "id": 2,
                "name": "Sheppard Heath"
            },
            {
                "id": 3,
                "name": "Dudley Ellison"
            },
            {
                "id": 4,
                "name": "Hanson Hanson"
            },
            {
                "id": 5,
                "name": "Travis Martin"
            }
        ],
        "voyages": [
            {
                "id": "5465338ba150830d349a4162",
                "name": "Jennings"
            }
        ]
    },
    {
        "_id": "5465338b4072b6284f0595c9",
        "index": 1,
        "guid": "b2af93fb-9cc9-4397-8bbb-68703fe08b26",
        "isActive": true,
        "picture": "http://placehold.it/32x32",
        "age": 23,
        "name": "Lowe Valencia",
        "gender": "male",
        "email": "lowevalencia@telequiet.com",
        "about": "Deserunt aliquip qui ad enim. Non et nisi in pariatur ea elit consectetur consequat cillum ut reprehenderit laboris. Velit culpa duis laboris sit.\r\n",
        "registered": "2014-06-17T12:21:05 -02:00",
        "friends": [
            {
                "id": 0,
                "name": "Silva Newton"
            },
            {
                "id": 1,
                "name": "Jewel Conner"
            },
            {
                "id": 2,
                "name": "Belinda Lucas"
            },
            {
                "id": 3,
                "name": "Marietta Grimes"
            },
            {
                "id": 4,
                "name": "Berta Harrington"
            },
            {
                "id": 5,
                "name": "Marsh Kline"
            }
        ],
        "voyages": [
            {
                "id": "5465338b524ed51ec28d775f",
                "name": "Darla"
            },
            {
                "id": "5465338b49fe9ebc4bcb0520",
                "name": "Malinda"
            }
        ]
    },
    {
        "_id": "5465338b9fc4d69be4ba6908",
        "index": 2,
        "guid": "a86ae507-b9b8-4682-b10a-7725fdf3f552",
        "isActive": false,
        "picture": "http://placehold.it/32x32",
        "age": 38,
        "name": "Rocha Downs",
        "gender": "male",
        "email": "rochadowns@telequiet.com",
        "about": "Qui duis proident Lorem deserunt consequat occaecat aute occaecat quis ea. Reprehenderit do ipsum nostrud amet ullamco ipsum nisi commodo. Ipsum aliqua Lorem commodo dolore irure nostrud quis fugiat proident eiusmod aliquip consequat. Incididunt sunt dolore consequat ut do ad fugiat aute id id consequat ipsum eu. Sint minim nulla veniam magna aliqua amet exercitation officia do velit voluptate in nisi.\r\n",
        "registered": "2014-11-03T13:28:14 -01:00",
        "friends": [
            {
                "id": 0,
                "name": "Howe Gaines"
            },
            {
                "id": 1,
                "name": "Enid Burt"
            },
            {
                "id": 2,
                "name": "Robertson Moses"
            },
            {
                "id": 3,
                "name": "Susan Mueller"
            },
            {
                "id": 4,
                "name": "Hendricks Lane"
            },
            {
                "id": 5,
                "name": "Stacey Madden"
            }
        ],
        "voyages": [
            {
                "id": "5465338bb5610a6c30d6e5ca",
                "name": "Helene"
            }
        ]
    },
    {
        "_id": "5465338bb61421f1b2757dd0",
        "index": 3,
        "guid": "3b205670-8f4c-4bf0-a69f-de27d7e3be6c",
        "isActive": false,
        "picture": "http://placehold.it/32x32",
        "age": 33,
        "name": "Jeanine Keller",
        "gender": "female",
        "email": "jeaninekeller@telequiet.com",
        "about": "Ea ullamco culpa nostrud sint officia cupidatat ad laborum deserunt. Laboris reprehenderit deserunt velit esse officia magna nisi labore ullamco mollit laboris. Sint velit ipsum pariatur excepteur velit culpa.\r\n",
        "registered": "2014-01-06T00:19:00 -01:00",
        "friends": [
            {
                "id": 0,
                "name": "Pamela Ramos"
            },
            {
                "id": 1,
                "name": "Shari Osborne"
            },
            {
                "id": 2,
                "name": "Jodie Stokes"
            },
            {
                "id": 3,
                "name": "Fisher Rosales"
            },
            {
                "id": 4,
                "name": "Obrien Hood"
            }
        ],
        "voyages": [
            {
                "id": "5465338b5cc4f7d65a7c9690",
                "name": "Randall"
            },
            {
                "id": "5465338b4d489a31ec727fa6",
                "name": "Harding"
            },
            {
                "id": "5465338b9b2c308b1c3c3ed1",
                "name": "Mae"
            }
        ]
    },
    {
        "_id": "5465338bdcb98e50113e2a1b",
        "index": 4,
        "guid": "956f5e2d-6e1c-48d7-92d2-e79fa9daef20",
        "isActive": false,
        "picture": "http://placehold.it/32x32",
        "age": 33,
        "name": "Freeman Hubbard",
        "gender": "male",
        "email": "freemanhubbard@telequiet.com",
        "about": "Nisi officia voluptate nisi duis eiusmod ullamco. Sint cillum culpa elit voluptate laborum elit. Fugiat ullamco id culpa sint incididunt cupidatat veniam eu aliqua anim. Officia nulla veniam laborum in amet enim fugiat dolore officia Lorem anim voluptate. Labore deserunt culpa mollit aliquip sint et et excepteur ut incididunt mollit esse velit et. Cupidatat do commodo ex aute ea.\r\n",
        "registered": "2014-05-29T19:10:07 -02:00",
        "friends": [
            {
                "id": 0,
                "name": "Lindsey Mann"
            },
            {
                "id": 1,
                "name": "Garza Dickson"
            },
            {
                "id": 2,
                "name": "Alyssa Peck"
            }
        ],
        "voyages": [
            {
                "id": "5465338b4d43478764f8f7d7",
                "name": "Montoya"
            },
            {
                "id": "5465338bd4b0e663d42a4ff6",
                "name": "Clarissa"
            },
            {
                "id": "5465338b6fa88ac6a362e328",
                "name": "Melva"
            }
        ]
    },
    {
        "_id": "5465338b761838991ef3741e",
        "index": 5,
        "guid": "1f0efdb7-860a-4678-bda7-538e032b5f34",
        "isActive": true,
        "picture": "http://placehold.it/32x32",
        "age": 26,
        "name": "Frankie Rowe",
        "gender": "female",
        "email": "frankierowe@telequiet.com",
        "about": "Consectetur id laboris fugiat mollit dolor ad mollit esse proident enim nisi minim. Non aliqua ad ullamco consequat Lorem aliquip proident pariatur quis labore laborum aute. Cupidatat cillum pariatur sunt anim do sint consequat exercitation ea duis pariatur occaecat adipisicing. Duis sit deserunt ex consectetur excepteur eu esse incididunt fugiat eu et deserunt nisi. Quis deserunt velit quis irure sint elit esse consequat. Est quis sit ea aliquip nostrud sit dolore.\r\n",
        "registered": "2014-08-18T06:32:42 -02:00",
        "friends": [
            {
                "id": 0,
                "name": "Cash Randall"
            },
            {
                "id": 1,
                "name": "Maria Blackwell"
            },
            {
                "id": 2,
                "name": "Kasey Christian"
            },
            {
                "id": 3,
                "name": "Bonner Donaldson"
            },
            {
                "id": 4,
                "name": "Rollins Hudson"
            }
        ],
        "voyages": [
            {
                "id": "5465338b6b95f9958033c20d",
                "name": "Mcgee"
            },
            {
                "id": "5465338b0924c2adbaa9e499",
                "name": "Valdez"
            },
            {
                "id": "5465338b2a297933f2a4b385",
                "name": "Irene"
            },
            {
                "id": "5465338b92a69f18995cbc10",
                "name": "Nadine"
            }
        ]
    },
    {
        "_id": "5465338b10e0341fcef06e2d",
        "index": 6,
        "guid": "2912bb48-358c-40e8-a63f-d83e6e218a6d",
        "isActive": false,
        "picture": "http://placehold.it/32x32",
        "age": 25,
        "name": "Jo Clayton",
        "gender": "female",
        "email": "joclayton@telequiet.com",
        "about": "Magna aute id quis cillum anim. Officia fugiat ipsum et adipisicing quis commodo id laboris deserunt. Elit elit fugiat reprehenderit dolor sint labore aute magna est in officia et dolore fugiat. Minim qui Lorem fugiat deserunt laboris ad non nulla laborum. Adipisicing officia amet ullamco consectetur aliqua veniam non.\r\n",
        "registered": "2014-08-02T11:03:43 -02:00",
        "friends": [
            {
                "id": 0,
                "name": "Rene Merrill"
            },
            {
                "id": 1,
                "name": "Hicks Rios"
            },
            {
                "id": 2,
                "name": "Rhoda Strong"
            },
            {
                "id": 3,
                "name": "Adrian Boyd"
            }
        ],
        "voyages": [
            {
                "id": "5465338b4a50c4fcc55c9f16",
                "name": "Marsha"
            },
            {
                "id": "5465338bc135bbe92978d255",
                "name": "Judith"
            },
            {
                "id": "5465338bc1b217a8d2554e25",
                "name": "Deana"
            },
            {
                "id": "5465338b458ca88bb0e79808",
                "name": "Audra"
            }
        ]
    },
    {
        "_id": "5465338b098930c896d2d505",
        "index": 7,
        "guid": "e8f5f027-63ce-4587-876d-da38f2026a2d",
        "isActive": true,
        "picture": "http://placehold.it/32x32",
        "age": 39,
        "name": "Murphy Ramsey",
        "gender": "male",
        "email": "murphyramsey@telequiet.com",
        "about": "Ex excepteur voluptate ad in adipisicing id commodo cupidatat do ad ad enim eu. Non sunt magna laboris cillum cillum do pariatur excepteur nisi velit exercitation sint. Aliqua sit ullamco incididunt non in Lorem amet laboris laboris. Irure quis ea dolor commodo proident ipsum consequat quis nostrud. Veniam irure labore sunt tempor Lorem consectetur quis voluptate.\r\n",
        "registered": "2014-01-30T09:05:43 -01:00",
        "friends": [
            {
                "id": 0,
                "name": "Valeria Murphy"
            },
            {
                "id": 1,
                "name": "Walton Rogers"
            },
            {
                "id": 2,
                "name": "Frye Powers"
            },
            {
                "id": 3,
                "name": "Lisa Yates"
            }
        ],
        "voyages": [
            {
                "id": "5465338b90ffa6ef0d4b2d01",
                "name": "Hobbs"
            },
            {
                "id": "5465338bc202c3cfb4eeb563",
                "name": "Frederick"
            },
            {
                "id": "5465338b2413d13fb349b089",
                "name": "Hardy"
            }
        ]
    },
    {
        "_id": "5465338b2ea8153ca4c21d0f",
        "index": 8,
        "guid": "48c83371-444d-48bf-9da7-9c61144a2aaa",
        "isActive": false,
        "picture": "http://placehold.it/32x32",
        "age": 21,
        "name": "Gould Moran",
        "gender": "male",
        "email": "gouldmoran@telequiet.com",
        "about": "Ullamco commodo consequat excepteur veniam ad. Ipsum culpa nisi velit ullamco qui quis consectetur elit laborum ipsum et proident reprehenderit. Aliqua labore irure enim quis sit nulla. Dolore consequat ex qui ad deserunt. Dolor Lorem aliquip ex aliqua mollit.\r\n",
        "registered": "2014-05-28T18:07:42 -02:00",
        "friends": [
            {
                "id": 0,
                "name": "Shields Schneider"
            },
            {
                "id": 1,
                "name": "Susie Woodard"
            },
            {
                "id": 2,
                "name": "Arline Mccarty"
            },
            {
                "id": 3,
                "name": "Joseph Watts"
            },
            {
                "id": 4,
                "name": "Cheryl Carpenter"
            },
            {
                "id": 5,
                "name": "Weeks Fitzpatrick"
            }
        ],
        "voyages": [
            {
                "id": "5465338b428ab1764c8d7a6f",
                "name": "Chan"
            },
            {
                "id": "5465338b911bccb5dd3aa42a",
                "name": "Celina"
            },
            {
                "id": "5465338b72adc0b409779367",
                "name": "Mona"
            }
        ]
    },
    {
        "_id": "5465338b6ab103878b77285e",
        "index": 9,
        "guid": "3bd2470a-f25b-46a8-8d70-57f2ca4edc55",
        "isActive": false,
        "picture": "http://placehold.it/32x32",
        "age": 21,
        "name": "Russo Long",
        "gender": "male",
        "email": "russolong@telequiet.com",
        "about": "Minim voluptate ad culpa in occaecat aute mollit ea officia cupidatat incididunt dolore qui. Ipsum voluptate fugiat sit adipisicing laboris. Sunt officia consequat elit sint reprehenderit ipsum sit sit labore nostrud nostrud irure qui. Exercitation ad eu magna incididunt nostrud elit.\r\n",
        "registered": "2014-01-14T20:42:16 -01:00",
        "friends": [
            {
                "id": 0,
                "name": "Pierce Mooney"
            },
            {
                "id": 1,
                "name": "Genevieve Livingston"
            },
            {
                "id": 2,
                "name": "Alicia Cabrera"
            },
            {
                "id": 3,
                "name": "Jennifer Stuart"
            },
            {
                "id": 4,
                "name": "Page Diaz"
            }
        ],
        "voyages": [
            {
                "id": "5465338be5d0db6c7c1870a7",
                "name": "Emma"
            },
            {
                "id": "5465338b45afc14aa35f1b3a",
                "name": "Simon"
            },
            {
                "id": "5465338b881d846c8bcfbd36",
                "name": "Mejia"
            },
            {
                "id": "5465338b99c6a850edb840e4",
                "name": "Blanchard"
            }
        ]
    },
    {
        "_id": "5465338bbe91cb8615b1f1ee",
        "index": 10,
        "guid": "3fad41f5-23e8-4eb9-a185-7e9ebb398476",
        "isActive": false,
        "picture": "http://placehold.it/32x32",
        "age": 24,
        "name": "Monroe Gomez",
        "gender": "male",
        "email": "monroegomez@telequiet.com",
        "about": "Ullamco culpa aliqua laborum amet anim. Veniam velit irure laborum sunt commodo deserunt voluptate ut nisi pariatur. Adipisicing reprehenderit laborum id mollit reprehenderit nisi elit duis. Fugiat ut nostrud magna occaecat culpa sit deserunt proident nostrud excepteur laboris. Do sint aute dolore duis proident duis et ea minim culpa veniam proident.\r\n",
        "registered": "2014-05-14T22:51:37 -02:00",
        "friends": [
            {
                "id": 0,
                "name": "Concepcion Allison"
            },
            {
                "id": 1,
                "name": "Hinton Collins"
            },
            {
                "id": 2,
                "name": "Aimee Gibson"
            },
            {
                "id": 3,
                "name": "Corinne Williams"
            },
            {
                "id": 4,
                "name": "Kara Crane"
            }
        ],
        "voyages": [
            {
                "id": "5465338b496d25cfe8a41fa3",
                "name": "Lenora"
            },
            {
                "id": "5465338b2cfec02bdf8070d3",
                "name": "Herring"
            },
            {
                "id": "5465338b0d85d73acfeca8b2",
                "name": "Berger"
            }
        ]
    },
    {
        "_id": "5465338b0304b5c7c0560d99",
        "index": 11,
        "guid": "aa268e88-7a71-4fc4-98fe-abbdcf844c25",
        "isActive": false,
        "picture": "http://placehold.it/32x32",
        "age": 34,
        "name": "Morton Sykes",
        "gender": "male",
        "email": "mortonsykes@telequiet.com",
        "about": "Amet in voluptate ad deserunt sit officia ex do eu esse nulla minim. Ipsum duis ea ex in et deserunt Lorem ad nisi id ex. Aliquip sint amet sint duis. Proident id sint magna pariatur enim laboris mollit quis pariatur cupidatat.\r\n",
        "registered": "2014-02-26T20:00:55 -01:00",
        "friends": [
            {
                "id": 0,
                "name": "Nita Sanchez"
            },
            {
                "id": 1,
                "name": "Savage White"
            },
            {
                "id": 2,
                "name": "Maribel Obrien"
            },
            {
                "id": 3,
                "name": "Rich Harding"
            },
            {
                "id": 4,
                "name": "English Mcpherson"
            }
        ],
        "voyages": [
            {
                "id": "5465338bc4544aa2a7a9779d",
                "name": "Neal"
            }
        ]
    },
    {
        "_id": "5465338b179e827c5426c00b",
        "index": 12,
        "guid": "ba8c7a54-2264-4020-988b-df7601b82e56",
        "isActive": true,
        "picture": "http://placehold.it/32x32",
        "age": 24,
        "name": "Lara Allen",
        "gender": "male",
        "email": "laraallen@telequiet.com",
        "about": "Cillum laboris proident nisi adipisicing eu incididunt esse. Esse ut consequat Lorem consequat pariatur. Aliqua anim enim eiusmod nostrud enim reprehenderit esse est eu ex velit fugiat pariatur voluptate. Sint anim consequat pariatur voluptate reprehenderit. Ad minim cupidatat cupidatat fugiat excepteur excepteur nulla pariatur est Lorem officia amet ad.\r\n",
        "registered": "2014-08-24T14:30:47 -02:00",
        "friends": [
            {
                "id": 0,
                "name": "Chandra Washington"
            },
            {
                "id": 1,
                "name": "Marjorie Sheppard"
            },
            {
                "id": 2,
                "name": "Daisy Tyler"
            },
            {
                "id": 3,
                "name": "Kelly Molina"
            }
        ],
        "voyages": [
            {
                "id": "5465338b0f60ad0de4b69354",
                "name": "Lawson"
            },
            {
                "id": "5465338b3771324f2ea9d155",
                "name": "Briggs"
            },
            {
                "id": "5465338b36b00f0e14d4bc5f",
                "name": "Dunlap"
            },
            {
                "id": "5465338bfcf0649a6b12a873",
                "name": "Katy"
            }
        ]
    },
    {
        "_id": "5465338b1ff39ce271fddc74",
        "index": 13,
        "guid": "ae51f903-5727-41e8-a6f4-7a75ee353581",
        "isActive": true,
        "picture": "http://placehold.it/32x32",
        "age": 21,
        "name": "Head Woods",
        "gender": "male",
        "email": "headwoods@telequiet.com",
        "about": "Excepteur proident esse duis consequat consequat amet in pariatur duis qui magna proident id. Culpa enim aliquip pariatur dolor. Cillum qui velit voluptate culpa occaecat reprehenderit dolore aute dolore dolor proident cillum.\r\n",
        "registered": "2014-03-19T21:43:26 -01:00",
        "friends": [
            {
                "id": 0,
                "name": "Lowery Gay"
            },
            {
                "id": 1,
                "name": "Wilkins Page"
            },
            {
                "id": 2,
                "name": "Tisha Lester"
            }
        ],
        "voyages": [
            {
                "id": "5465338b4dc7d77a11abedb2",
                "name": "Leila"
            },
            {
                "id": "5465338be37469c4f603c727",
                "name": "Mattie"
            },
            {
                "id": "5465338bbf5fa242e1f75ff9",
                "name": "Maryanne"
            }
        ]
    },
    {
        "_id": "5465338bc135ddb55f84651a",
        "index": 14,
        "guid": "3e0a0274-3935-47d7-8d34-b28a82d30a1e",
        "isActive": false,
        "picture": "http://placehold.it/32x32",
        "age": 40,
        "name": "Mayra Mcconnell",
        "gender": "female",
        "email": "mayramcconnell@telequiet.com",
        "about": "Ad tempor qui dolor et duis in ipsum. Sunt esse velit dolor enim cillum irure adipisicing ea sunt quis in. Aliqua duis commodo do eiusmod sunt consectetur. Cupidatat in sit aliqua nisi velit nostrud voluptate incididunt adipisicing proident. Enim do eu eiusmod aliquip pariatur eu reprehenderit magna ea enim ex sit magna dolor. Tempor duis cupidatat amet reprehenderit ut incididunt ad mollit. Non officia nostrud est elit deserunt sunt tempor fugiat eiusmod.\r\n",
        "registered": "2014-04-18T08:02:40 -02:00",
        "friends": [
            {
                "id": 0,
                "name": "Moreno Mayo"
            },
            {
                "id": 1,
                "name": "Lorena Wade"
            },
            {
                "id": 2,
                "name": "Bradley Vasquez"
            },
            {
                "id": 3,
                "name": "Lawrence Robles"
            }
        ],
        "voyages": [
            {
                "id": "5465338b5cd718966afc0244",
                "name": "Florence"
            },
            {
                "id": "5465338b134100f6f9d7ad8d",
                "name": "Latasha"
            }
        ]
    },
    {
        "_id": "5465338b8c87b79901631d1d",
        "index": 15,
        "guid": "0a8be61f-c8b0-4079-b503-27581107bef1",
        "isActive": true,
        "picture": "http://placehold.it/32x32",
        "age": 24,
        "name": "Kristie Spencer",
        "gender": "female",
        "email": "kristiespencer@telequiet.com",
        "about": "Ea ipsum ex sit exercitation deserunt sunt laborum nulla officia tempor id nulla. Ex sunt laboris esse dolore. Do culpa nisi quis ullamco Lorem consequat ullamco do reprehenderit eu in labore. Deserunt Lorem ea excepteur officia consequat aute. Dolore cillum magna Lorem reprehenderit adipisicing dolore nulla cillum esse mollit.\r\n",
        "registered": "2014-03-28T14:17:35 -01:00",
        "friends": [
            {
                "id": 0,
                "name": "Fry Baird"
            },
            {
                "id": 1,
                "name": "Parker Hess"
            },
            {
                "id": 2,
                "name": "Ward Morgan"
            }
        ],
        "voyages": [
            {
                "id": "5465338bb5e567355a3eaa8a",
                "name": "Briana"
            },
            {
                "id": "5465338b0bd4de883c2d1122",
                "name": "Fannie"
            },
            {
                "id": "5465338ba01abbb94020a770",
                "name": "Britney"
            },
            {
                "id": "5465338bb5d9b851d62f4d96",
                "name": "Cassie"
            }
        ]
    },
    {
        "_id": "5465338b827e8b1324679a71",
        "index": 16,
        "guid": "beedc507-7a70-4105-a950-a5f90e23fabe",
        "isActive": false,
        "picture": "http://placehold.it/32x32",
        "age": 38,
        "name": "Short Brennan",
        "gender": "male",
        "email": "shortbrennan@telequiet.com",
        "about": "Officia sit elit ad duis tempor qui. Elit ea sit pariatur irure. Velit culpa et Lorem ut deserunt ipsum reprehenderit laborum laboris nulla culpa. Quis eu nulla laboris dolore veniam mollit nostrud elit adipisicing labore consequat fugiat. Adipisicing ut non enim excepteur voluptate voluptate consectetur proident est adipisicing sint.\r\n",
        "registered": "2014-08-04T18:48:15 -02:00",
        "friends": [
            {
                "id": 0,
                "name": "Dawson Kerr"
            },
            {
                "id": 1,
                "name": "Orr Pruitt"
            },
            {
                "id": 2,
                "name": "Tricia Stark"
            },
            {
                "id": 3,
                "name": "Holly Cantrell"
            }
        ],
        "voyages": [
            {
                "id": "5465338bda4c88d8e8fe01cb",
                "name": "Eunice"
            },
            {
                "id": "5465338b0bb80acb662f16b6",
                "name": "Lillian"
            }
        ]
    },
    {
        "_id": "5465338b2796e8c3d92dcbee",
        "index": 17,
        "guid": "e7b05768-0472-49f0-8528-3f0811a2b073",
        "isActive": false,
        "picture": "http://placehold.it/32x32",
        "age": 40,
        "name": "Jaclyn Noble",
        "gender": "female",
        "email": "jaclynnoble@telequiet.com",
        "about": "Veniam aliqua nostrud tempor mollit nostrud nulla tempor nostrud ea sint ex deserunt enim. Consequat deserunt irure anim fugiat id quis consequat sit ea adipisicing. Occaecat occaecat consectetur dolore aute Lorem. Nisi proident irure incididunt minim dolore commodo.\r\n",
        "registered": "2014-02-18T09:14:00 -01:00",
        "friends": [
            {
                "id": 0,
                "name": "Olson Barrett"
            },
            {
                "id": 1,
                "name": "Janelle Cortez"
            },
            {
                "id": 2,
                "name": "Rosalie Ferrell"
            },
            {
                "id": 3,
                "name": "Blankenship Britt"
            },
            {
                "id": 4,
                "name": "Kaufman Calhoun"
            }
        ],
        "voyages": [
            {
                "id": "5465338bcc717570e687ad07",
                "name": "Beatriz"
            },
            {
                "id": "5465338b0b94089e0f7df1a5",
                "name": "Bridgett"
            },
            {
                "id": "5465338b458da206b07f92ea",
                "name": "Rosario"
            },
            {
                "id": "5465338b28b02aedd5606719",
                "name": "Case"
            }
        ]
    },
    {
        "_id": "5465338b29787aa4946aa6cf",
        "index": 18,
        "guid": "f399351f-b34e-4228-a0b4-2a340ea44e3d",
        "isActive": true,
        "picture": "http://placehold.it/32x32",
        "age": 33,
        "name": "Denise Mcintosh",
        "gender": "female",
        "email": "denisemcintosh@telequiet.com",
        "about": "Incididunt aute aliquip in est. Deserunt elit qui eu labore cillum labore. Adipisicing quis sunt et ut tempor dolore eu ipsum tempor quis. Sint tempor mollit cillum et occaecat.\r\n",
        "registered": "2014-02-12T02:05:42 -01:00",
        "friends": [
            {
                "id": 0,
                "name": "Darlene Blevins"
            },
            {
                "id": 1,
                "name": "Dolores Little"
            },
            {
                "id": 2,
                "name": "Lou Waller"
            },
            {
                "id": 3,
                "name": "Kathryn Fisher"
            }
        ],
        "voyages": [
            {
                "id": "5465338b163bbfe76eaf9935",
                "name": "Rosanna"
            }
        ]
    },
    {
        "_id": "5465338b414c969008cf5431",
        "index": 19,
        "guid": "a633a4bc-dff4-4603-beaf-302be9708949",
        "isActive": false,
        "picture": "http://placehold.it/32x32",
        "age": 23,
        "name": "Sue Potts",
        "gender": "female",
        "email": "suepotts@telequiet.com",
        "about": "Nisi ullamco adipisicing eiusmod Lorem commodo sit excepteur ex elit voluptate. Cupidatat ad aute qui cupidatat esse amet ex consectetur. Nisi cillum enim sunt reprehenderit culpa.\r\n",
        "registered": "2014-07-09T13:49:04 -02:00",
        "friends": [
            {
                "id": 0,
                "name": "Kari Valentine"
            },
            {
                "id": 1,
                "name": "Gardner Frederick"
            },
            {
                "id": 2,
                "name": "Johanna Silva"
            },
            {
                "id": 3,
                "name": "Trisha Carlson"
            }
        ],
        "voyages": [
            {
                "id": "5465338ba0aceabb4327024b",
                "name": "Marina"
            },
            {
                "id": "5465338b4dc35e1158a86e1a",
                "name": "Barron"
            },
            {
                "id": "5465338b99d9a5e0a820c12c",
                "name": "Antonia"
            },
            {
                "id": "5465338b3ce05c9a36efa88c",
                "name": "Virgie"
            }
        ]
    },
    {
        "_id": "5465338ba730202756f5b889",
        "index": 20,
        "guid": "d945535f-e7a5-45f6-b26c-05eaad5c870f",
        "isActive": true,
        "picture": "http://placehold.it/32x32",
        "age": 25,
        "name": "Jerri Bishop",
        "gender": "female",
        "email": "jerribishop@telequiet.com",
        "about": "Commodo aute occaecat ipsum nostrud reprehenderit reprehenderit magna nulla anim minim. Consequat sint amet adipisicing Lorem enim magna. Labore cillum enim irure enim tempor.\r\n",
        "registered": "2014-10-17T10:44:35 -02:00",
        "friends": [
            {
                "id": 0,
                "name": "Alisa Mullen"
            },
            {
                "id": 1,
                "name": "Kristina Salinas"
            },
            {
                "id": 2,
                "name": "Park Maddox"
            },
            {
                "id": 3,
                "name": "Traci Rose"
            },
            {
                "id": 4,
                "name": "Kellie Osborn"
            },
            {
                "id": 5,
                "name": "Ethel Soto"
            }
        ],
        "voyages": [
            {
                "id": "5465338b26c65e39233433ab",
                "name": "Holmes"
            }
        ]
    },
    {
        "_id": "5465338bec0d48c5adc95862",
        "index": 21,
        "guid": "567ca791-61e1-46c4-9e63-a43b37c2ec7f",
        "isActive": true,
        "picture": "http://placehold.it/32x32",
        "age": 32,
        "name": "Lopez Meyers",
        "gender": "male",
        "email": "lopezmeyers@telequiet.com",
        "about": "Aute veniam irure deserunt voluptate adipisicing sunt aute ex laboris magna est cupidatat consequat. Exercitation veniam laborum ut voluptate nostrud dolor laborum eu laborum consectetur anim ut nisi. Reprehenderit sint anim ex ut officia. Irure est adipisicing ullamco dolor dolor magna ad.\r\n",
        "registered": "2014-01-20T19:11:31 -01:00",
        "friends": [
            {
                "id": 0,
                "name": "Crosby Robinson"
            },
            {
                "id": 1,
                "name": "Flynn Hewitt"
            },
            {
                "id": 2,
                "name": "Monica Spears"
            },
            {
                "id": 3,
                "name": "Beasley Bonner"
            },
            {
                "id": 4,
                "name": "Lori Whitney"
            },
            {
                "id": 5,
                "name": "Mcintyre Hammond"
            }
        ],
        "voyages": [
            {
                "id": "5465338b85a80927bf596015",
                "name": "Robyn"
            },
            {
                "id": "5465338b1314f955299301f8",
                "name": "Martinez"
            }
        ]
    },
    {
        "_id": "5465338bf00244cba752f939",
        "index": 22,
        "guid": "2a5482b3-5df7-4575-90ee-5b55a33ed3e2",
        "isActive": true,
        "picture": "http://placehold.it/32x32",
        "age": 26,
        "name": "Cooke Knox",
        "gender": "male",
        "email": "cookeknox@telequiet.com",
        "about": "Sit ullamco consequat consectetur laboris excepteur et pariatur velit dolor commodo cupidatat nostrud fugiat. Fugiat ea est quis laborum in nulla elit excepteur magna. Elit minim velit reprehenderit ut nisi. Sint et id aute excepteur minim irure cupidatat excepteur et consequat mollit. Minim exercitation duis deserunt culpa occaecat aute duis esse dolore sunt magna.\r\n",
        "registered": "2014-06-06T09:35:34 -02:00",
        "friends": [
            {
                "id": 0,
                "name": "Salinas Macias"
            },
            {
                "id": 1,
                "name": "Angelica Norris"
            },
            {
                "id": 2,
                "name": "Cobb Goodwin"
            },
            {
                "id": 3,
                "name": "Mcdowell Aguirre"
            },
            {
                "id": 4,
                "name": "Serrano Hunt"
            }
        ],
        "voyages": [
            {
                "id": "5465338be84500a7950269e5",
                "name": "Louella"
            },
            {
                "id": "5465338b5e7c3eaa7953497a",
                "name": "Landry"
            },
            {
                "id": "5465338b3d2fe64a4090c425",
                "name": "Wagner"
            },
            {
                "id": "5465338b7d7c35653f89dc77",
                "name": "Mathews"
            }
        ]
    },
    {
        "_id": "5465338ba520b15af22ffba3",
        "index": 23,
        "guid": "cc6d5062-e0eb-4e9a-81d8-d3c2fc794036",
        "isActive": false,
        "picture": "http://placehold.it/32x32",
        "age": 20,
        "name": "Rodriquez Dunlap",
        "gender": "male",
        "email": "rodriquezdunlap@telequiet.com",
        "about": "Ad minim ad aute ullamco fugiat sit cillum ad id officia minim sunt amet et. Consequat duis cillum et consectetur eiusmod aliqua veniam. Magna excepteur cupidatat excepteur nostrud dolore duis nulla enim consequat eiusmod laborum aliquip in aliqua. Reprehenderit excepteur laborum nulla fugiat velit ipsum aute nostrud.\r\n",
        "registered": "2014-11-03T07:13:26 -01:00",
        "friends": [
            {
                "id": 0,
                "name": "Ashlee Rivera"
            },
            {
                "id": 1,
                "name": "Mcmahon Dotson"
            },
            {
                "id": 2,
                "name": "Kidd Edwards"
            }
        ],
        "voyages": [
            {
                "id": "5465338b3e288018e08359b2",
                "name": "Lara"
            }
        ]
    },
    {
        "_id": "5465338bc6730222614ee89f",
        "index": 24,
        "guid": "9d76ca77-9c19-48c0-9286-aa9395d985b4",
        "isActive": false,
        "picture": "http://placehold.it/32x32",
        "age": 20,
        "name": "Reeves Mccray",
        "gender": "male",
        "email": "reevesmccray@telequiet.com",
        "about": "Laboris occaecat veniam nulla commodo voluptate nostrud elit est enim anim. Labore Lorem in do ipsum ea quis nisi esse amet incididunt enim Lorem nulla eu. Qui enim eu esse enim eiusmod incididunt enim laborum magna eu. Ea ea eu nulla labore adipisicing laboris consequat reprehenderit quis eu adipisicing dolore deserunt sit. Ex nisi nisi eu nisi nostrud mollit deserunt qui cupidatat. Incididunt nostrud enim ea dolore. Anim enim cupidatat consectetur amet.\r\n",
        "registered": "2014-07-14T03:06:29 -02:00",
        "friends": [
            {
                "id": 0,
                "name": "Nixon Cohen"
            },
            {
                "id": 1,
                "name": "Stuart Deleon"
            },
            {
                "id": 2,
                "name": "Aguilar England"
            },
            {
                "id": 3,
                "name": "Valencia Miles"
            },
            {
                "id": 4,
                "name": "Tabatha Herman"
            }
        ],
        "voyages": [
            {
                "id": "5465338b99892484a8c2c8f5",
                "name": "Walls"
            },
            {
                "id": "5465338baf5a81e30662b643",
                "name": "Clarke"
            }
        ]
    },
    {
        "_id": "5465338b154eab5762680f3d",
        "index": 25,
        "guid": "a8af699e-ca59-4dfc-8267-a41c59bc8620",
        "isActive": false,
        "picture": "http://placehold.it/32x32",
        "age": 25,
        "name": "Simone Mcdaniel",
        "gender": "female",
        "email": "simonemcdaniel@telequiet.com",
        "about": "Sunt ex esse magna voluptate deserunt officia non ut irure reprehenderit. Elit commodo fugiat aliqua labore. Consequat ad dolor officia duis id. Ad sint cupidatat laboris est nisi. Aliquip irure aute culpa eu in nostrud amet officia velit adipisicing et reprehenderit. Magna aliqua eiusmod veniam dolor minim qui. Aliqua aute aliqua exercitation commodo aliqua deserunt excepteur ipsum pariatur eu.\r\n",
        "registered": "2014-09-01T23:48:43 -02:00",
        "friends": [
            {
                "id": 0,
                "name": "Anne Fulton"
            },
            {
                "id": 1,
                "name": "Chen Rojas"
            },
            {
                "id": 2,
                "name": "Johnson Snow"
            },
            {
                "id": 3,
                "name": "Graham Norton"
            },
            {
                "id": 4,
                "name": "Lucas Kinney"
            }
        ],
        "voyages": [
            {
                "id": "5465338b379e3cf751af2050",
                "name": "Samantha"
            },
            {
                "id": "5465338bcdcbf6c876e066b1",
                "name": "Cooley"
            },
            {
                "id": "5465338be099fa6fc15a8a50",
                "name": "Frieda"
            },
            {
                "id": "5465338b9361e791e5c13f2f",
                "name": "Herman"
            }
        ]
    },
    {
        "_id": "5465338be7dd89eff58032ad",
        "index": 26,
        "guid": "ca79c4c9-15ff-4eaf-b04e-8a472866f14e",
        "isActive": false,
        "picture": "http://placehold.it/32x32",
        "age": 39,
        "name": "Alyce Sexton",
        "gender": "female",
        "email": "alycesexton@telequiet.com",
        "about": "Amet in consequat ex duis Lorem aute culpa do anim ad velit. Laboris amet voluptate nostrud culpa. Veniam non incididunt tempor consequat dolor reprehenderit consequat irure elit. Nisi eiusmod laborum ex non. Veniam in quis incididunt voluptate fugiat minim magna duis ullamco excepteur nisi esse Lorem ut.\r\n",
        "registered": "2014-03-02T03:42:08 -01:00",
        "friends": [
            {
                "id": 0,
                "name": "Liliana Carney"
            },
            {
                "id": 1,
                "name": "Rodriguez Walker"
            },
            {
                "id": 2,
                "name": "Walsh Foster"
            },
            {
                "id": 3,
                "name": "Hood Ware"
            },
            {
                "id": 4,
                "name": "Raymond Cardenas"
            }
        ],
        "voyages": [
            {
                "id": "5465338bb20e1707cce98e71",
                "name": "Elena"
            },
            {
                "id": "5465338b09f4baff8bc36131",
                "name": "Lawanda"
            }
        ]
    },
    {
        "_id": "5465338bbe73be1eb4caa0e5",
        "index": 27,
        "guid": "747e4ec3-a423-44ac-b094-aad3e83ee16c",
        "isActive": true,
        "picture": "http://placehold.it/32x32",
        "age": 22,
        "name": "Stephanie Poole",
        "gender": "female",
        "email": "stephaniepoole@telequiet.com",
        "about": "Eiusmod ullamco officia magna incididunt adipisicing cillum irure. Dolor commodo sunt commodo cillum tempor. Nulla esse quis excepteur esse incididunt excepteur enim ea non ullamco incididunt et consequat elit. Do laboris ex ut ad adipisicing qui. Mollit magna eu magna eiusmod occaecat commodo.\r\n",
        "registered": "2014-01-21T18:39:29 -01:00",
        "friends": [
            {
                "id": 0,
                "name": "Tina Keith"
            },
            {
                "id": 1,
                "name": "Alford Mercer"
            },
            {
                "id": 2,
                "name": "Rosales Ratliff"
            },
            {
                "id": 3,
                "name": "Earnestine Knapp"
            }
        ],
        "voyages": [
            {
                "id": "5465338b1640c1ddff403d9f",
                "name": "Hillary"
            },
            {
                "id": "5465338b8646176e175045c1",
                "name": "Lauri"
            },
            {
                "id": "5465338be6b5b2f10edb7848",
                "name": "Maura"
            }
        ]
    },
    {
        "_id": "5465338bef83e94f0d36e3c8",
        "index": 28,
        "guid": "dd91527e-17fb-47fc-8ed1-31706817c542",
        "isActive": false,
        "picture": "http://placehold.it/32x32",
        "age": 26,
        "name": "Marci Burris",
        "gender": "female",
        "email": "marciburris@telequiet.com",
        "about": "Esse officia nisi enim do deserunt enim reprehenderit aute. Occaecat mollit dolore veniam id proident nisi commodo. Proident proident do irure labore irure aliqua reprehenderit. Id exercitation enim velit id labore cupidatat nostrud velit consequat. Ex amet cupidatat amet mollit et proident ipsum et occaecat nisi do. Sunt ut dolor labore laborum tempor amet do velit deserunt tempor nostrud do officia.\r\n",
        "registered": "2014-03-28T14:53:35 -01:00",
        "friends": [
            {
                "id": 0,
                "name": "Finch David"
            },
            {
                "id": 1,
                "name": "Roseann Tanner"
            },
            {
                "id": 2,
                "name": "Mitzi Cherry"
            },
            {
                "id": 3,
                "name": "Lakeisha Dawson"
            },
            {
                "id": 4,
                "name": "Fran Mendez"
            },
            {
                "id": 5,
                "name": "Mandy Hancock"
            }
        ],
        "voyages": [
            {
                "id": "5465338b29bbe0b9ad8d2a67",
                "name": "Rutledge"
            },
            {
                "id": "5465338b91bb94c2adcce6bd",
                "name": "Burnett"
            },
            {
                "id": "5465338b6cd1e64d65917ac5",
                "name": "Margret"
            },
            {
                "id": "5465338b9464961f01247e05",
                "name": "Pitts"
            }
        ]
    },
    {
        "_id": "5465338bb07df785d6520cb4",
        "index": 29,
        "guid": "c21b474a-3b84-410d-9332-3859929667cb",
        "isActive": true,
        "picture": "http://placehold.it/32x32",
        "age": 29,
        "name": "Barnes Holcomb",
        "gender": "male",
        "email": "barnesholcomb@telequiet.com",
        "about": "Sit officia ea voluptate laboris cupidatat amet duis cupidatat. Cillum cupidatat non duis ipsum dolor mollit sunt consectetur eiusmod enim veniam eu fugiat. In dolor nulla incididunt anim voluptate officia pariatur qui in consectetur eiusmod ad exercitation.\r\n",
        "registered": "2014-02-07T18:47:07 -01:00",
        "friends": [
            {
                "id": 0,
                "name": "Paige Moreno"
            },
            {
                "id": 1,
                "name": "Munoz Preston"
            },
            {
                "id": 2,
                "name": "Rhodes Vazquez"
            },
            {
                "id": 3,
                "name": "Larson Banks"
            },
            {
                "id": 4,
                "name": "Bender Stafford"
            },
            {
                "id": 5,
                "name": "Sallie Russell"
            }
        ],
        "voyages": [
            {
                "id": "5465338b0917fe2333cfcc82",
                "name": "Delaney"
            },
            {
                "id": "5465338bf09a78aeaec37c80",
                "name": "Nellie"
            },
            {
                "id": "5465338b26fefbf471f91885",
                "name": "Rita"
            }
        ]
    },
    {
        "_id": "5465338bb8f1eba0f8b42682",
        "index": 30,
        "guid": "ba2ce305-3eef-431a-91b7-5781346ccb7e",
        "isActive": false,
        "picture": "http://placehold.it/32x32",
        "age": 24,
        "name": "Adams King",
        "gender": "male",
        "email": "adamsking@telequiet.com",
        "about": "Duis mollit laborum in fugiat irure culpa enim velit. Aliqua minim eiusmod velit ex qui ad tempor minim. Et aliqua reprehenderit Lorem voluptate cupidatat ipsum elit laborum sit nostrud ut labore dolore. Nulla amet est cupidatat anim quis. Id occaecat reprehenderit et irure. Sit nostrud esse laborum sint aliquip quis commodo. Consectetur voluptate nostrud nulla consequat anim labore est elit amet consectetur ex.\r\n",
        "registered": "2014-01-22T13:27:13 -01:00",
        "friends": [
            {
                "id": 0,
                "name": "Barbra Bell"
            },
            {
                "id": 1,
                "name": "Schultz James"
            },
            {
                "id": 2,
                "name": "Eva Fletcher"
            },
            {
                "id": 3,
                "name": "Hilary Carey"
            },
            {
                "id": 4,
                "name": "Brandi Palmer"
            },
            {
                "id": 5,
                "name": "Flores Whitaker"
            }
        ],
        "voyages": [
            {
                "id": "5465338b3a45b84287ec83bf",
                "name": "Sophie"
            },
            {
                "id": "5465338b68f0385113317c0d",
                "name": "Knight"
            }
        ]
    },
    {
        "_id": "5465338b84e0f38e60f5f0ae",
        "index": 31,
        "guid": "6b60a405-f444-485c-96b4-9a69121f48ac",
        "isActive": false,
        "picture": "http://placehold.it/32x32",
        "age": 31,
        "name": "Petra Glover",
        "gender": "female",
        "email": "petraglover@telequiet.com",
        "about": "Eiusmod est fugiat velit excepteur est sint excepteur adipisicing mollit cupidatat ullamco culpa pariatur et. Mollit voluptate dolore proident ad id duis ullamco irure consequat dolore reprehenderit ipsum pariatur dolore. Eu mollit ipsum in culpa est exercitation laborum ea ad exercitation tempor excepteur incididunt nostrud. Amet qui ipsum sit amet esse consequat minim incididunt sunt. Sint ea cupidatat consectetur enim laborum deserunt mollit qui non. Anim excepteur eiusmod officia exercitation reprehenderit eu irure aute occaecat eiusmod.\r\n",
        "registered": "2014-06-05T07:35:29 -02:00",
        "friends": [
            {
                "id": 0,
                "name": "Gena Guy"
            },
            {
                "id": 1,
                "name": "Valenzuela Sherman"
            },
            {
                "id": 2,
                "name": "Opal Hughes"
            }
        ],
        "voyages": [
            {
                "id": "5465338b802fe4ba317b0750",
                "name": "Mollie"
            },
            {
                "id": "5465338b30867b490a4e8edc",
                "name": "Elsa"
            },
            {
                "id": "5465338ba3d3e89698300f6a",
                "name": "Thompson"
            }
        ]
    }
]