[
    {
        "name": "Alban",
        "id": "0",
        "email": "alban.chimon@telenet.com",
        "voyages": "0",
        "age": "19"
    },
    {
        "name": "Koala Secret",
        "id": "1",
        "email": "koakoa@yahoo.fr",
        "voyages": "0",
        "age": "24"
    },
    {
        "name": "Kephren",
        "id": "2",
        "email": "kevin.dupont@hotmail.com",
        "voyages": "1",
        "age": "24"
    },
    {
        "name": "Lolap",
        "id": "3",
        "email": "laura.pilon@gmail.com",
        "voyages": "2",
        "age": "28"
    },
    {
        "name": "Indy Jones",
        "id": "4",
        "email": "stephane.lemeunier@orange.fr",
        "voyages": "0",
        "age": "35"
    },
    {
        "name": "Elulula",
        "id": "5",
        "email": "egris.tilu@wanadoo.fr",
        "voyages": "0",
        "age": "32"
    },
    {
        "name": "Zazou",
        "id": "6",
        "email": "zazou.le.tigrou@telenet.net",
        "voyages": "1",
        "age": "28"
    },
    {
        "name": "Hiurka",
        "id": "7",
        "email": "helenephisoline@gmail.com",
        "voyages": "2",
        "age": "30"
    },
    {
        "name": "Gégé",
        "id": "8",
        "email": "gerard.piquet@hotmail.fr",
        "voyages": "3",
        "age": "57"
    },
    {
        "name": "Kim45",
        "id": "9",
        "email": "dragonfire45@hotmail.fr",
        "voyages": "2",
        "age": "17"
    },
    {
        "name": "Marc Henry",
        "id": "10",
        "email": "mh.duprimaut@laposte.net",
        "voyages": "0",
        "age": "40"
    },
    {
        "name": "Frieddda",
        "id": "11",
        "email": "frieddd@laposte.net",
        "voyages": "5",
        "age": "52"
    },
        {
        "name": "Foura Micro",
        "id": "12",
        "email": "foura.micro@gmail.com",
        "voyages": "6",
        "age": "46"
    },
    {
        "name": "Mimilolo",
        "id": "13",
        "email": "espalalamimi@wanadoo.fr",
        "voyages": "7",
        "age": "22"
    },
    {
        "name": "Le Ténébreux",
        "id": "14",
        "email": "rumplestiltskin@gold.fr",
        "voyages": "7",
        "age": "70"
    }
]